{".class":"MypyFile","_fullname":"src.gui.widgets.base_page","future_import_flags":[],"is_partial_stub_package":false,"is_stub":false,"names":{".class":"SymbolTable","BasePage":{".class":"SymbolTableNode","kind":"Gdef","node":{".class":"TypeInfo","_promote":[],"abstract_attributes":[],"alt_promote":null,"bases":["PySide6.QtWidgets.QWidget","src.gui.widgets.toast.ToastMixin"],"dataclass_transform_spec":null,"declared_metaclass":null,"defn":{".class":"ClassDef","fullname":"src.gui.widgets.base_page.BasePage","name":"BasePage","type_vars":[]},"deletable_attributes":[],"deprecated":null,"flags":[],"fullname":"src.gui.widgets.base_page.BasePage","has_param_spec_type":false,"metaclass_type":null,"metadata":{},"module_name":"src.gui.widgets.base_page","mro":["src.gui.widgets.base_page.BasePage","PySide6.QtWidgets.QWidget","PySide6.QtCore.QObject","PySide6.QtGui.QPaintDevice","shiboken6.Shiboken.Object","src.gui.widgets.toast.ToastMixin","builtins.object"],"names":{".class":"SymbolTable","__init__":{".class":"SymbolTableNode","kind":"Mdef","node":{".class":"FuncDef","abstract_status":0,"arg_kinds":[0,1],"arg_names":["self","main_window"],"dataclass_transform_spec":null,"deprecated":null,"flags":[],"fullname":"src.gui.widgets.base_page.BasePage.__init__","name":"__init__","original_first_arg":"self","type":null}},"_add_back_button":{".class":"SymbolTableNode","kind":"Mdef","node":{".class":"FuncDef","abstract_status":0,"arg_kinds":[0,0,1],"arg_names":["self","layout","target"],"dataclass_transform_spec":null,"deprecated":null,"flags":["is_trivial_self"],"fullname":"src.gui.widgets.base_page.BasePage._add_back_button","name":"_add_back_button","original_first_arg":"self","type":{".class":"CallableType","arg_kinds":[0,0,1],"arg_names":["self","layout","target"],"arg_types":["src.gui.widgets.base_page.BasePage","PySide6.QtWidgets.QVBoxLayout","builtins.str"],"fallback":"builtins.function","from_concatenate":false,"implicit":false,"imprecise_arg_kinds":false,"is_bound":false,"is_ellipsis_args":false,"name":"_add_back_button of BasePage","ret_type":"PySide6.QtWidgets.QHBoxLayout","type_guard":null,"type_is":null,"unpack_kwargs":false,"variables":[]}}},"_add_export_button":{".class":"SymbolTableNode","kind":"Mdef","node":{".class":"FuncDef","abstract_status":0,"arg_kinds":[0,0,0,1],"arg_names":["self","layout","on_export","label"],"dataclass_transform_spec":null,"deprecated":null,"flags":["is_trivial_self"],"fullname":"src.gui.widgets.base_page.BasePage._add_export_button","name":"_add_export_button","original_first_arg":"self","type":{".class":"CallableType","arg_kinds":[0,0,0,1],"arg_names":["self","layout","on_export","label"],"arg_types":["src.gui.widgets.base_page.BasePage","PySide6.QtWidgets.QVBoxLayout",{".class":"AnyType","missing_import_name":null,"source_any":null,"type_of_any":1},"builtins.str"],"fallback":"builtins.function","from_concatenate":false,"implicit":false,"imprecise_arg_kinds":false,"is_bound":false,"is_ellipsis_args":false,"name":"_add_export_button of BasePage","ret_type":{".class":"AnyType","missing_import_name":null,"source_any":null,"type_of_any":1},"type_guard":null,"type_is":null,"unpack_kwargs":false,"variables":[]}}},"_export_active_malote":{".class":"SymbolTableNode","kind":"Mdef","node":{".class":"FuncDef","abstract_status":0,"arg_kinds":[0],"arg_names":["self"],"dataclass_transform_spec":null,"deprecated":null,"flags":[],"fullname":"src.gui.widgets.base_page.BasePage._export_active_malote","name":"_export_active_malote","original_first_arg":"self","type":null}},"_handle_error":{".class":"SymbolTableNode","kind":"Mdef","node":{".class":"FuncDef","abstract_status":0,"arg_kinds":[0,0,1],"arg_names":["self","e","context"],"dataclass_transform_spec":null,"deprecated":null,"flags":[],"fullname":"src.gui.widgets.base_page.BasePage._handle_error","name":"_handle_error","original_first_arg":"self","type":null}},"_keyboard_nav":{".class":"SymbolTableNode","implicit":true,"kind":"Mdef","node":{".class":"Var","flags":["explicit_self_type","is_ready","is_inferred"],"fullname":"src.gui.widgets.base_page.BasePage._keyboard_nav","name":"_keyboard_nav","setter_type":null,"type":{".class":"Instance","args":[{".class":"TupleType","implicit":false,"items":["PySide6.QtWidgets.QWidget","PySide6.QtWidgets.QLineEdit",{".class":"CallableType","arg_kinds":[2,4],"arg_names":[null,null],"arg_types":[{".class":"AnyType","missing_import_name":null,"source_any":null,"type_of_any":4},{".class":"AnyType","missing_import_name":null,"source_any":null,"type_of_any":4}],"fallback":"builtins.function","from_concatenate":false,"implicit":false,"imprecise_arg_kinds":false,"is_bound":false,"is_ellipsis_args":true,"name":null,"ret_type":{".class":"AnyType","missing_import_name":null,"source_any":null,"type_of_any":4},"type_guard":null,"type_is":null,"unpack_kwargs":false,"variables":[]}],"partial_fallback":{".class":"Instance","args":[{".class":"AnyType","missing_import_name":null,"source_any":null,"type_of_any":6}],"extra_attrs":null,"type_ref":"builtins.tuple"}}],"extra_attrs":null,"type_ref":"builtins.list"}}},"_move_row":{".class":"SymbolTableNode","kind":"Mdef","node":{".class":"FuncDef","abstract_status":0,"arg_kinds":[0,0,0],"arg_names":["self","widget","direction"],"dataclass_transform_spec":null,"deprecated":null,"flags":[],"fullname":"src.gui.widgets.base_page.BasePage._move_row","name":"_move_row","original_first_arg":"self","type":null}},"_mw":{".class":"SymbolTableNode","implicit":true,"kind":"Mdef","node":{".class":"Var","flags":["is_ready","is_inferred"],"fullname":"src.gui.widgets.base_page.BasePage._mw","name":"_mw","setter_type":null,"type":{".class":"AnyType","missing_import_name":null,"source_any":null,"type_of_any":1}}},"_scaffold":{".class":"SymbolTableNode","kind":"Mdef","node":{".class":"FuncDef","abstract_status":0,"arg_kinds":[0],"arg_names":["self"],"dataclass_transform_spec":null,"deprecated":null,"flags":["is_trivial_self"],"fullname":"src.gui.widgets.base_page.BasePage._scaffold","name":"_scaffold","original_first_arg":"self","type":{".class":"CallableType","arg_kinds":[0],"arg_names":["self"],"arg_types":["src.gui.widgets.base_page.BasePage"],"fallback":"builtins.function","from_concatenate":false,"implicit":false,"imprecise_arg_kinds":false,"is_bound":false,"is_ellipsis_args":false,"name":"_scaffold of BasePage","ret_type":"PySide6.QtWidgets.QVBoxLayout","type_guard":null,"type_is":null,"unpack_kwargs":false,"variables":[]}}},"_shortcut_searches":{".class":"SymbolTableNode","implicit":true,"kind":"Mdef","node":{".class":"Var","flags":["explicit_self_type","is_ready","is_inferred"],"fullname":"src.gui.widgets.base_page.BasePage._shortcut_searches","name":"_shortcut_searches","setter_type":null,"type":{".class":"Instance","args":[{".class":"TupleType","implicit":false,"items":["builtins.str","PySide6.QtWidgets.QLineEdit"],"partial_fallback":{".class":"Instance","args":[{".class":"AnyType","missing_import_name":null,"source_any":null,"type_of_any":6}],"extra_attrs":null,"type_ref":"builtins.tuple"}}],"extra_attrs":null,"type_ref":"builtins.list"}}},"_shortcut_widgets":{".class":"SymbolTableNode","implicit":true,"kind":"Mdef","node":{".class":"Var","flags":["explicit_self_type","is_ready","is_inferred"],"fullname":"src.gui.widgets.base_page.BasePage._shortcut_widgets","name":"_shortcut_widgets","setter_type":null,"type":{".class":"Instance","args":[{".class":"AnyType","missing_import_name":null,"source_any":null,"type_of_any":4},{".class":"AnyType","missing_import_name":null,"source_any":null,"type_of_any":4}],"extra_attrs":null,"type_ref":"builtins.dict"}}},"clear_keyboard_nav":{".class":"SymbolTableNode","kind":"Mdef","node":{".class":"FuncDef","abstract_status":0,"arg_kinds":[0],"arg_names":["self"],"dataclass_transform_spec":null,"deprecated":null,"flags":[],"fullname":"src.gui.widgets.base_page.BasePage.clear_keyboard_nav","name":"clear_keyboard_nav","original_first_arg":"self","type":null}},"eventFilter":{".class":"SymbolTableNode","kind":"Mdef","node":{".class":"FuncDef","abstract_status":0,"arg_kinds":[0,0,0],"arg_names":["self","obj","event"],"dataclass_transform_spec":null,"deprecated":null,"flags":[],"fullname":"src.gui.widgets.base_page.BasePage.eventFilter","name":"eventFilter","original_first_arg":"self","type":null}},"register_keyboard_nav":{".class":"SymbolTableNode","kind":"Mdef","node":{".class":"FuncDef","abstract_status":0,"arg_kinds":[0,0,0,0],"arg_names":["self","widget","search","on_enter"],"dataclass_transform_spec":null,"deprecated":null,"flags":["is_trivial_self"],"fullname":"src.gui.widgets.base_page.BasePage.register_keyboard_nav","name":"register_keyboard_nav","original_first_arg":"self","type":{".class":"CallableType","arg_kinds":[0,0,0,0],"arg_names":["self","widget","search","on_enter"],"arg_types":["src.gui.widgets.base_page.BasePage","PySide6.QtWidgets.QWidget","PySide6.QtWidgets.QLineEdit",{".class":"CallableType","arg_kinds":[2,4],"arg_names":[null,null],"arg_types":[{".class":"AnyType","missing_import_name":null,"source_any":null,"type_of_any":4},{".class":"AnyType","missing_import_name":null,"source_any":null,"type_of_any":4}],"fallback":"builtins.function","from_concatenate":false,"implicit":false,"imprecise_arg_kinds":false,"is_bound":false,"is_ellipsis_args":true,"name":null,"ret_type":{".class":"AnyType","missing_import_name":null,"source_any":null,"type_of_any":4},"type_guard":null,"type_is":null,"unpack_kwargs":false,"variables":[]}],"fallback":"builtins.function","from_concatenate":false,"implicit":false,"imprecise_arg_kinds":false,"is_bound":false,"is_ellipsis_args":false,"name":"register_keyboard_nav of BasePage","ret_type":{".class":"AnyType","missing_import_name":null,"source_any":null,"type_of_any":1},"type_guard":null,"type_is":null,"unpack_kwargs":false,"variables":[]}}},"set_shortcuts_visible":{".class":"SymbolTableNode","kind":"Mdef","node":{".class":"FuncDef","abstract_status":0,"arg_kinds":[0,0],"arg_names":["self","show"],"dataclass_transform_spec":null,"deprecated":null,"flags":["is_trivial_self"],"fullname":"src.gui.widgets.base_page.BasePage.set_shortcuts_visible","name":"set_shortcuts_visible","original_first_arg":"self","type":{".class":"CallableType","arg_kinds":[0,0],"arg_names":["self","show"],"arg_types":["src.gui.widgets.base_page.BasePage","builtins.bool"],"fallback":"builtins.function","from_concatenate":false,"implicit":false,"imprecise_arg_kinds":false,"is_bound":false,"is_ellipsis_args":false,"name":"set_shortcuts_visible of BasePage","ret_type":{".class":"AnyType","missing_import_name":null,"source_any":null,"type_of_any":1},"type_guard":null,"type_is":null,"unpack_kwargs":false,"variables":[]}}}},"self_type":{".class":"TypeVarType","default":{".class":"AnyType","missing_import_name":null,"source_any":null,"type_of_any":4},"fullname":"src.gui.widgets.base_page.BasePage.Self","id":0,"name":"Self","namespace":"","upper_bound":"src.gui.widgets.base_page.BasePage","values":[],"variance":0},"slots":null,"tuple_type":null,"type_vars":[],"typeddict_type":null}},"Callable":{".class":"SymbolTableNode","cross_ref":"typing.Callable","kind":"Gdef"},"QHBoxLayout":{".class":"SymbolTableNode","cross_ref":"PySide6.QtWidgets.QHBoxLayout","kind":"Gdef"},"QKeyEvent":{".class":"SymbolTableNode","cross_ref":"PySide6.QtGui.QKeyEvent","kind":"Gdef"},"QLineEdit":{".class":"SymbolTableNode","cross_ref":"PySide6.QtWidgets.QLineEdit","kind":"Gdef"},"QSizePolicy":{".class":"SymbolTableNode","cross_ref":"PySide6.QtWidgets.QSizePolicy","kind":"Gdef"},"QVBoxLayout":{".class":"SymbolTableNode","cross_ref":"PySide6.QtWidgets.QVBoxLayout","kind":"Gdef"},"QWidget":{".class":"SymbolTableNode","cross_ref":"PySide6.QtWidgets.QWidget","kind":"Gdef"},"Qt":{".class":"SymbolTableNode","cross_ref":"PySide6.QtCore.Qt","kind":"Gdef"},"SHORTCUT_LABELS":{".class":"SymbolTableNode","cross_ref":"src.gui.constants.SHORTCUT_LABELS","kind":"Gdef"},"ToastMixin":{".class":"SymbolTableNode","cross_ref":"src.gui.widgets.toast.ToastMixin","kind":"Gdef"},"__annotations__":{".class":"SymbolTableNode","kind":"Gdef","node":{".class":"Var","flags":["is_ready"],"fullname":"src.gui.widgets.base_page.__annotations__","name":"__annotations__","setter_type":null,"type":{".class":"Instance","args":["builtins.str",{".class":"AnyType","missing_import_name":null,"source_any":null,"type_of_any":6}],"extra_attrs":null,"type_ref":"builtins.dict"}}},"__doc__":{".class":"SymbolTableNode","kind":"Gdef","node":{".class":"Var","flags":["is_ready"],"fullname":"src.gui.widgets.base_page.__doc__","name":"__doc__","setter_type":null,"type":"builtins.str"}},"__file__":{".class":"SymbolTableNode","kind":"Gdef","node":{".class":"Var","flags":["is_ready"],"fullname":"src.gui.widgets.base_page.__file__","name":"__file__","setter_type":null,"type":"builtins.str"}},"__name__":{".class":"SymbolTableNode","kind":"Gdef","node":{".class":"Var","flags":["is_ready"],"fullname":"src.gui.widgets.base_page.__name__","name":"__name__","setter_type":null,"type":"builtins.str"}},"__package__":{".class":"SymbolTableNode","kind":"Gdef","node":{".class":"Var","flags":["is_ready"],"fullname":"src.gui.widgets.base_page.__package__","name":"__package__","setter_type":null,"type":"builtins.str"}},"__spec__":{".class":"SymbolTableNode","kind":"Gdef","node":{".class":"Var","flags":["is_ready"],"fullname":"src.gui.widgets.base_page.__spec__","name":"__spec__","setter_type":null,"type":"_frozen_importlib.ModuleSpec"}},"_open_file_location":{".class":"SymbolTableNode","kind":"Gdef","node":{".class":"FuncDef","abstract_status":0,"arg_kinds":[0],"arg_names":["path"],"dataclass_transform_spec":null,"deprecated":null,"flags":[],"fullname":"src.gui.widgets.base_page._open_file_location","name":"_open_file_location","original_first_arg":"path","type":{".class":"CallableType","arg_kinds":[0],"arg_names":["path"],"arg_types":["builtins.str"],"fallback":"builtins.function","from_concatenate":false,"implicit":false,"imprecise_arg_kinds":false,"is_bound":false,"is_ellipsis_args":false,"name":"_open_file_location","ret_type":{".class":"AnyType","missing_import_name":null,"source_any":null,"type_of_any":1},"type_guard":null,"type_is":null,"unpack_kwargs":false,"variables":[]}}},"export_with_fallback":{".class":"SymbolTableNode","kind":"Gdef","node":{".class":"FuncDef","abstract_status":0,"arg_kinds":[0,0,1],"arg_names":["page","export_fn","no_data_msg"],"dataclass_transform_spec":null,"deprecated":null,"flags":[],"fullname":"src.gui.widgets.base_page.export_with_fallback","name":"export_with_fallback","original_first_arg":"page","type":null}},"make_button":{".class":"SymbolTableNode","cross_ref":"src.gui.widgets.buttons.make_button","kind":"Gdef"},"make_hbox":{".class":"SymbolTableNode","kind":"Gdef","node":{".class":"FuncDef","abstract_status":0,"arg_kinds":[1,1],"arg_names":["margins","spacing"],"dataclass_transform_spec":null,"deprecated":null,"flags":[],"fullname":"src.gui.widgets.base_page.make_hbox","name":"make_hbox","original_first_arg":"margins","type":null}},"make_tab":{".class":"SymbolTableNode","kind":"Gdef","node":{".class":"FuncDef","abstract_status":0,"arg_kinds":[1,1],"arg_names":["margins","spacing"],"dataclass_transform_spec":null,"deprecated":null,"flags":[],"fullname":"src.gui.widgets.base_page.make_tab","name":"make_tab","original_first_arg":"margins","type":null}}},"path":"/home/jvanery/Projects/RAC - Registros Alto Custo/src/gui/widgets/base_page.py"}